[{"id":1,"name":"台北市環保兩用袋大 <1PC個 x 1 x 1PC個>","emoji":"🍽️","price":5,"category":"暢銷商品","desc":"Uber Eats 菜單品項","badge":null,"soldCount":117,"image":"assets/images/menu/ue-s1JXMVZgRn-VBVnfUt_NFQ-1.webp"},{"id":2,"name":"義美 傳統料理豆腐(非基改) 300g <300g克 x 1 x 1Box盒>","emoji":"🍽️","price":23,"category":"暢銷商品","desc":"Uber Eats 菜單品項","badge":null,"soldCount":134,"image":"assets/images/menu/ue-s1JXMVZgRn-VBVnfUt_NFQ-2.webp"},{"id":3,"name":"履歷玉米 2入(每盒約380克) <1Box盒 x 1 x 1BOX盒>","emoji":"🍽️","price":48,"category":"暢銷商品","desc":"Uber Eats 菜單品項","badge":null,"soldCount":151,"image":"assets/images/menu/ue-s1JXMVZgRn-VBVnfUt_NFQ-3.webp"},{"id":4,"name":"【非籠飼】御品園土雞蛋(放牧冷藏) 400g <400g克 x 1 x 1BOX盒>","emoji":"🍽️","price":134,"category":"暢銷商品","desc":"Uber Eats 菜單品項","badge":null,"soldCount":168,"image":"assets/images/menu/ue-s1JXMVZgRn-VBVnfUt_NFQ-4.webp"},{"id":5,"name":"有機金針菇(每包約200g±10%) <1Bag袋 x 1 x 1Bag袋>","emoji":"🍽️","price":10,"category":"暢銷商品","desc":"Uber Eats 菜單品項","badge":null,"soldCount":185,"image":"assets/images/menu/ue-s1JXMVZgRn-VBVnfUt_NFQ-5.webp"},{"id":6,"name":"瑞穗鮮乳-全脂1858ml※實際到貨效期約4天以上 <1858ml毫升 x 1 x 1Bottle瓶>","emoji":"🍽️","price":170,"category":"暢銷商品","desc":"Uber Eats 菜單品項","badge":null,"soldCount":202,"image":"assets/images/menu/ue-s1JXMVZgRn-VBVnfUt_NFQ-6.webp"},{"id":7,"name":"履歷珍珠芭樂(每袋2顆/約750克) <1Bag袋 x 1 x 1Bag袋>","emoji":"🍽️","price":92,"category":"暢銷商品","desc":"Uber Eats 菜單品項","badge":null,"soldCount":219,"image":"assets/images/menu/ue-s1JXMVZgRn-VBVnfUt_NFQ-7.webp"},{"id":8,"name":"產銷履歷冷藏去骨雞腿排(約200克)-貼體包裝※因配送關係實際到貨效期約2-3天 <1Box盒 x 1 x 1BOX盒>","emoji":"🍽️","price":103,"category":"暢銷商品","desc":"Uber Eats 菜單品項","badge":null,"soldCount":236,"image":"assets/images/menu/ue-s1JXMVZgRn-VBVnfUt_NFQ-8.webp"},{"id":9,"name":"冷凍栽種藍莓 <400g克 x 1 x 1Pack包>","emoji":"🍽️","price":234,"category":"暢銷商品","desc":"Uber Eats 菜單品項","badge":null,"soldCount":253,"image":"assets/images/menu/ue-s1JXMVZgRn-VBVnfUt_NFQ-9.webp"},{"id":10,"name":"紐西蘭洋蔥(2粒/每粒約200g±10%) <1PC個 x 1 x 2PC個>","emoji":"🍽️","price":35,"category":"暢銷商品","desc":"Uber Eats 菜單品項","badge":null,"soldCount":270,"image":"assets/images/menu/ue-s1JXMVZgRn-VBVnfUt_NFQ-10.webp"},{"id":11,"name":"履歷老薑(每袋約300克) <1Bag袋 x 1 x 1Bag袋>","emoji":"🍽️","price":72,"category":"暢銷商品","desc":"Uber Eats 菜單品項","badge":null,"soldCount":287,"image":"assets/images/menu/ue-s1JXMVZgRn-VBVnfUt_NFQ-11.webp"},{"id":12,"name":"統一 PH9.0鹼性離子水800ml毫升 <800ml毫升 x 1 x 1Bottle瓶>","emoji":"🍽️","price":28,"category":"暢銷商品","desc":"Uber Eats 菜單品項","badge":null,"soldCount":304,"image":"assets/images/menu/ue-s1JXMVZgRn-VBVnfUt_NFQ-12.webp"},{"id":13,"name":"義美無加糖豆奶1000ml※實際到貨效期約4天以上 <1000ml毫升 x 1 x 1Bottle瓶>","emoji":"🍽️","price":48,"category":"暢銷商品","desc":"Uber Eats 菜單品項","badge":null,"soldCount":321,"image":"assets/images/menu/ue-s1JXMVZgRn-VBVnfUt_NFQ-13.webp"},{"id":14,"name":"可口可樂ZERO迷你罐200ml <200ml毫升 x 1 x 8Can罐>","emoji":"🍽️","price":127,"category":"暢銷商品","desc":"Uber Eats 菜單品項","badge":null,"soldCount":338,"image":"assets/images/menu/ue-s1JXMVZgRn-VBVnfUt_NFQ-14.webp"},{"id":15,"name":"立得清酒精擦濕巾90抽 <90PC抽 x 1 x 1Pack包>","emoji":"🍽️","price":109,"category":"暢銷商品","desc":"Uber Eats 菜單品項","badge":null,"soldCount":355,"image":"assets/images/menu/ue-s1JXMVZgRn-VBVnfUt_NFQ-15.webp"},{"id":16,"name":"越南娃娃菜200g/袋 <1Bag袋 x 1 x 1Bag袋>","emoji":"🍽️","price":48,"category":"新鮮蔬果、蔬食主義","desc":"Uber Eats 菜單品項","badge":null,"soldCount":372,"image":"assets/images/menu/ue-s1JXMVZgRn-VBVnfUt_NFQ-16.webp"},{"id":17,"name":"Hoya植物肉乾-法式松露風味 <50g克 x 1 x 1Bag袋>","emoji":"🍽️","price":39,"category":"新鮮蔬果、蔬食主義","desc":"Uber Eats 菜單品項","badge":null,"soldCount":389,"image":"assets/images/menu/ue-s1JXMVZgRn-VBVnfUt_NFQ-17.webp"},{"id":18,"name":"越南娃娃菜200g/袋 <1Bag袋 x 1 x 1Bag袋>","emoji":"🍽️","price":48,"category":"新鮮蔬果、蔬食主義","desc":"Uber Eats 菜單品項","badge":null,"soldCount":406,"image":"assets/images/menu/ue-s1JXMVZgRn-VBVnfUt_NFQ-18.webp"},{"id":19,"name":"履歷香菇150g/盒 <1Box盒 x 1 x 1BOX盒>","emoji":"🍽️","price":48,"category":"新鮮蔬果、蔬食主義","desc":"Uber Eats 菜單品項","badge":null,"soldCount":423,"image":"assets/images/menu/ue-s1JXMVZgRn-VBVnfUt_NFQ-19.webp"},{"id":20,"name":"有機小黃瓜(每盒約300克±10%) <1Box盒 x 1 x 1BOX盒>","emoji":"🍽️","price":52,"category":"新鮮蔬果、蔬食主義","desc":"Uber Eats 菜單品項","badge":null,"soldCount":440,"image":"assets/images/menu/ue-s1JXMVZgRn-VBVnfUt_NFQ-20.webp"},{"id":21,"name":"履歷老薑(每袋約300克) <1Bag袋 x 1 x 1Bag袋>","emoji":"🍽️","price":72,"category":"新鮮蔬果、蔬食主義","desc":"Uber Eats 菜單品項","badge":null,"soldCount":457,"image":"assets/images/menu/ue-s1JXMVZgRn-VBVnfUt_NFQ-21.webp"},{"id":22,"name":"履歷玉米 2入(每盒約380克) <1Box盒 x 1 x 1BOX盒>","emoji":"🍽️","price":48,"category":"新鮮蔬果、蔬食主義","desc":"Uber Eats 菜單品項","badge":null,"soldCount":474,"image":"assets/images/menu/ue-s1JXMVZgRn-VBVnfUt_NFQ-22.webp"},{"id":23,"name":"有機金針菇(每包約200g±10%) <1Bag袋 x 1 x 1Bag袋>","emoji":"🍽️","price":10,"category":"新鮮蔬果、蔬食主義","desc":"Uber Eats 菜單品項","badge":null,"soldCount":491,"image":"assets/images/menu/ue-s1JXMVZgRn-VBVnfUt_NFQ-23.webp"},{"id":24,"name":"進口盒裝藍莓(每盒約125克±10%) <1Box盒 x 1 x 2Box盒>","emoji":"🍽️","price":190,"category":"新鮮蔬果、蔬食主義","desc":"Uber Eats 菜單品項","badge":null,"soldCount":108,"image":"assets/images/menu/ue-s1JXMVZgRn-VBVnfUt_NFQ-24.webp"}]