[{"id":1,"name":"蒜了蒜了美乃滋牛堡 + 奶昔","emoji":"🍽️","price":376,"category":"精選商品","desc":"Uber Eats 菜單品項","badge":null,"soldCount":117,"image":"assets/images/menu/ue-wr561sjtXdKDci5FdEzXLA-1.jpg"},{"id":2,"name":"三巴肯瓊風味炸雞堡 + 奶昔","emoji":"🍽️","price":376,"category":"精選商品","desc":"Uber Eats 菜單品項","badge":null,"soldCount":134,"image":"assets/images/menu/ue-wr561sjtXdKDci5FdEzXLA-2.jpg"},{"id":3,"name":"三巴手作花生泥","emoji":"🍽️","price":300,"category":"精選商品","desc":"Uber Eats 菜單品項","badge":null,"soldCount":151,"image":"assets/images/menu/ue-wr561sjtXdKDci5FdEzXLA-3.jpg"},{"id":4,"name":"蒜了蒜了美乃滋","emoji":"🍽️","price":300,"category":"精選商品","desc":"Uber Eats 菜單品項","badge":null,"soldCount":168,"image":"assets/images/menu/ue-wr561sjtXdKDci5FdEzXLA-4.jpg"},{"id":5,"name":"牛肝菌菇菇寶貝","emoji":"🍽️","price":330,"category":"精選商品","desc":"Uber Eats 菜單品項","badge":null,"soldCount":185,"image":"assets/images/menu/ue-wr561sjtXdKDci5FdEzXLA-5.jpg"},{"id":6,"name":"酪極酪梨莎莎","emoji":"🍽️","price":330,"category":"精選商品","desc":"Uber Eats 菜單品項","badge":null,"soldCount":202,"image":"assets/images/menu/ue-wr561sjtXdKDci5FdEzXLA-6.jpg"},{"id":7,"name":"墨佬香料手撕豬","emoji":"🍽️","price":400,"category":"精選商品","desc":"Uber Eats 菜單品項","badge":null,"soldCount":219,"image":"assets/images/menu/ue-wr561sjtXdKDci5FdEzXLA-7.jpg"},{"id":8,"name":"三巴肯瓊炸雞堡","emoji":"🍽️","price":300,"category":"精選商品","desc":"Uber Eats 菜單品項","badge":null,"soldCount":236,"image":"assets/images/menu/ue-wr561sjtXdKDci5FdEzXLA-8.jpg"},{"id":9,"name":"巴嘎墨墨辣肉醬","emoji":"🍽️","price":300,"category":"精選商品","desc":"Uber Eats 菜單品項","badge":null,"soldCount":253,"image":"assets/images/menu/ue-wr561sjtXdKDci5FdEzXLA-9.jpg"},{"id":10,"name":"海鹽香蕉尬酪梨奶昔","emoji":"🍽️","price":190,"category":"精選商品","desc":"Uber Eats 菜單品項","badge":null,"soldCount":270,"image":"assets/images/menu/ue-wr561sjtXdKDci5FdEzXLA-10.jpg"},{"id":11,"name":"重焙新巴客可可奶昔","emoji":"🍽️","price":180,"category":"精選商品","desc":"Uber Eats 菜單品項","badge":null,"soldCount":287,"image":"assets/images/menu/ue-wr561sjtXdKDci5FdEzXLA-11.jpg"},{"id":12,"name":"鬼椒from the hell","emoji":"🍽️","price":330,"category":"精選商品","desc":"Uber Eats 菜單品項","badge":null,"soldCount":304,"image":"assets/images/menu/ue-wr561sjtXdKDci5FdEzXLA-12.jpg"},{"id":13,"name":"三巴肯瓊風味炸雞堡 + 奶昔","emoji":"🍽️","price":376,"category":"訂購指定商品即享優惠","desc":"Uber Eats 菜單品項","badge":null,"soldCount":321,"image":"assets/images/menu/ue-wr561sjtXdKDci5FdEzXLA-13.jpg"},{"id":14,"name":"蒜了蒜了美乃滋牛堡 + 奶昔","emoji":"🍽️","price":376,"category":"訂購指定商品即享優惠","desc":"Uber Eats 菜單品項","badge":null,"soldCount":338,"image":"assets/images/menu/ue-wr561sjtXdKDci5FdEzXLA-14.jpg"},{"id":15,"name":"蒜了蒜了美乃滋牛堡 + 奶昔","emoji":"🍽️","price":376,"category":"您專屬的推薦商品","desc":"Uber Eats 菜單品項","badge":null,"soldCount":355,"image":"assets/images/menu/ue-wr561sjtXdKDci5FdEzXLA-15.jpg"},{"id":16,"name":"蒜了蒜了美乃滋","emoji":"🍽️","price":300,"category":"您專屬的推薦商品","desc":"Uber Eats 菜單品項","badge":null,"soldCount":372,"image":"assets/images/menu/ue-wr561sjtXdKDci5FdEzXLA-16.jpg"},{"id":17,"name":"三巴手作花生泥","emoji":"🍽️","price":300,"category":"您專屬的推薦商品","desc":"Uber Eats 菜單品項","badge":null,"soldCount":389,"image":"assets/images/menu/ue-wr561sjtXdKDci5FdEzXLA-17.jpg"},{"id":18,"name":"三巴肯瓊炸雞堡","emoji":"🍽️","price":300,"category":"您專屬的推薦商品","desc":"Uber Eats 菜單品項","badge":null,"soldCount":406,"image":"assets/images/menu/ue-wr561sjtXdKDci5FdEzXLA-18.jpg"},{"id":19,"name":"牛肝菌菇菇寶貝","emoji":"🍽️","price":330,"category":"您專屬的推薦商品","desc":"Uber Eats 菜單品項","badge":null,"soldCount":423,"image":"assets/images/menu/ue-wr561sjtXdKDci5FdEzXLA-19.jpg"},{"id":20,"name":"蒜了蒜了美乃滋","emoji":"🍽️","price":300,"category":"Burger 漢堡","desc":"Uber Eats 菜單品項","badge":null,"soldCount":440,"image":"assets/images/menu/ue-wr561sjtXdKDci5FdEzXLA-20.jpg"},{"id":21,"name":"三巴手作花生泥","emoji":"🍽️","price":300,"category":"Burger 漢堡","desc":"Uber Eats 菜單品項","badge":null,"soldCount":457,"image":"assets/images/menu/ue-wr561sjtXdKDci5FdEzXLA-21.jpg"},{"id":22,"name":"巴嘎墨墨辣肉醬","emoji":"🍽️","price":300,"category":"Burger 漢堡","desc":"Uber Eats 菜單品項","badge":null,"soldCount":474,"image":"assets/images/menu/ue-wr561sjtXdKDci5FdEzXLA-22.jpg"},{"id":23,"name":"酪極酪梨莎莎","emoji":"🍽️","price":330,"category":"Burger 漢堡","desc":"Uber Eats 菜單品項","badge":null,"soldCount":491,"image":"assets/images/menu/ue-wr561sjtXdKDci5FdEzXLA-23.jpg"},{"id":24,"name":"牛肝菌菇菇寶貝","emoji":"🍽️","price":330,"category":"Burger 漢堡","desc":"Uber Eats 菜單品項","badge":null,"soldCount":108,"image":"assets/images/menu/ue-wr561sjtXdKDci5FdEzXLA-24.jpg"}]